LICENSE-MIT
MANIFEST.in
README.rst
docopt.py
setup.cfg
setup.py
docopt_unicode.egg-info/PKG-INFO
docopt_unicode.egg-info/SOURCES.txt
docopt_unicode.egg-info/dependency_links.txt
docopt_unicode.egg-info/top_level.txt
examples/arguments_example.py
examples/calculator_example.py
examples/config_file_example.py
examples/counted_example.py
examples/interactive_example.py
examples/naval_fate.py
examples/odd_even_example.py
examples/options_example.py
examples/options_shortcut_example.py
examples/quick_example.py
examples/validation_example.py
examples/git/git.py
examples/git/git_add.py
examples/git/git_branch.py
examples/git/git_checkout.py
examples/git/git_clone.py
examples/git/git_commit.py
examples/git/git_push.py
examples/git/git_remote.py